{
  "version": "6",
  "dialect": "sqlite",
  "id": "ac7a0831-73c5-41f7-bcab-00d7af829c1f",
  "prevId": "00000000-0000-0000-0000-000000000000",
  "tables": {
    "doc_comments": {
      "name": "doc_comments",
      "columns": {
        "id": {
          "name": "id",
          "type": "text",
          "primaryKey": true,
          "notNull": true,
          "autoincrement": false
        },
        "doc_id": {
          "name": "doc_id",
          "type": "text",
          "primaryKey": false,
          "notNull": true,
          "autoincrement": false
        },
        "author_id": {
          "name": "author_id",
          "type": "text",
          "primaryKey": false,
          "notNull": true,
          "autoincrement": false
        },
        "body": {
          "name": "body",
          "type": "text",
          "primaryKey": false,
          "notNull": true,
          "autoincrement": false
        },
        "resolved": {
          "name": "resolved",
          "type": "integer",
          "primaryKey": false,
          "notNull": true,
          "autoincrement": false
        },
        "created_at_label": {
          "name": "created_at_label",
          "type": "text",
          "primaryKey": false,
          "notNull": true,
          "autoincrement": false
        }
      },
      "indexes": {},
      "foreignKeys": {
        "doc_comments_doc_id_documents_id_fk": {
          "name": "doc_comments_doc_id_documents_id_fk",
          "tableFrom": "doc_comments",
          "tableTo": "documents",
          "columnsFrom": [
            "doc_id"
          ],
          "columnsTo": [
            "id"
          ],
          "onDelete": "cascade",
          "onUpdate": "no action"
        },
        "doc_comments_author_id_members_id_fk": {
          "name": "doc_comments_author_id_members_id_fk",
          "tableFrom": "doc_comments",
          "tableTo": "members",
          "columnsFrom": [
            "author_id"
          ],
          "columnsTo": [
            "id"
          ],
          "onDelete": "no action",
          "onUpdate": "no action"
        }
      },
      "compositePrimaryKeys": {},
      "uniqueConstraints": {},
      "checkConstraints": {}
    },
    "doc_issue_links": {
      "name": "doc_issue_links",
      "columns": {
        "doc_id": {
          "name": "doc_id",
          "type": "text",
          "primaryKey": false,
          "notNull": true,
          "autoincrement": false
        },
        "issue_key": {
          "name": "issue_key",
          "type": "text",
          "primaryKey": false,
          "notNull": true,
          "autoincrement": false
        }
      },
      "indexes": {
        "doc_issue_links_unique": {
          "name": "doc_issue_links_unique",
          "columns": [
            "doc_id",
            "issue_key"
          ],
          "isUnique": true
        }
      },
      "foreignKeys": {
        "doc_issue_links_doc_id_documents_id_fk": {
          "name": "doc_issue_links_doc_id_documents_id_fk",
          "tableFrom": "doc_issue_links",
          "tableTo": "documents",
          "columnsFrom": [
            "doc_id"
          ],
          "columnsTo": [
            "id"
          ],
          "onDelete": "cascade",
          "onUpdate": "no action"
        },
        "doc_issue_links_issue_key_issues_key_fk": {
          "name": "doc_issue_links_issue_key_issues_key_fk",
          "tableFrom": "doc_issue_links",
          "tableTo": "issues",
          "columnsFrom": [
            "issue_key"
          ],
          "columnsTo": [
            "key"
          ],
          "onDelete": "cascade",
          "onUpdate": "no action"
        }
      },
      "compositePrimaryKeys": {},
      "uniqueConstraints": {},
      "checkConstraints": {}
    },
    "documents": {
      "name": "documents",
      "columns": {
        "id": {
          "name": "id",
          "type": "text",
          "primaryKey": true,
          "notNull": true,
          "autoincrement": false
        },
        "scope": {
          "name": "scope",
          "type": "text",
          "primaryKey": false,
          "notNull": true,
          "autoincrement": false
        },
        "project_id": {
          "name": "project_id",
          "type": "text",
          "primaryKey": false,
          "notNull": false,
          "autoincrement": false
        },
        "title": {
          "name": "title",
          "type": "text",
          "primaryKey": false,
          "notNull": true,
          "autoincrement": false
        },
        "directory": {
          "name": "directory",
          "type": "text",
          "primaryKey": false,
          "notNull": true,
          "autoincrement": false
        },
        "body": {
          "name": "body",
          "type": "text",
          "primaryKey": false,
          "notNull": true,
          "autoincrement": false
        },
        "updated_at_label": {
          "name": "updated_at_label",
          "type": "text",
          "primaryKey": false,
          "notNull": true,
          "autoincrement": false
        }
      },
      "indexes": {
        "documents_project": {
          "name": "documents_project",
          "columns": [
            "project_id"
          ],
          "isUnique": false
        }
      },
      "foreignKeys": {
        "documents_project_id_projects_id_fk": {
          "name": "documents_project_id_projects_id_fk",
          "tableFrom": "documents",
          "tableTo": "projects",
          "columnsFrom": [
            "project_id"
          ],
          "columnsTo": [
            "id"
          ],
          "onDelete": "cascade",
          "onUpdate": "no action"
        }
      },
      "compositePrimaryKeys": {},
      "uniqueConstraints": {},
      "checkConstraints": {}
    },
    "feishu_notifications": {
      "name": "feishu_notifications",
      "columns": {
        "id": {
          "name": "id",
          "type": "text",
          "primaryKey": true,
          "notNull": true,
          "autoincrement": false
        },
        "trigger": {
          "name": "trigger",
          "type": "text",
          "primaryKey": false,
          "notNull": true,
          "autoincrement": false
        },
        "target_group": {
          "name": "target_group",
          "type": "text",
          "primaryKey": false,
          "notNull": true,
          "autoincrement": false
        },
        "payload_json": {
          "name": "payload_json",
          "type": "text",
          "primaryKey": false,
          "notNull": true,
          "autoincrement": false
        },
        "status": {
          "name": "status",
          "type": "text",
          "primaryKey": false,
          "notNull": true,
          "autoincrement": false
        },
        "created_at": {
          "name": "created_at",
          "type": "text",
          "primaryKey": false,
          "notNull": true,
          "autoincrement": false
        }
      },
      "indexes": {},
      "foreignKeys": {},
      "compositePrimaryKeys": {},
      "uniqueConstraints": {},
      "checkConstraints": {}
    },
    "feishu_queries": {
      "name": "feishu_queries",
      "columns": {
        "id": {
          "name": "id",
          "type": "text",
          "primaryKey": true,
          "notNull": true,
          "autoincrement": false
        },
        "command": {
          "name": "command",
          "type": "text",
          "primaryKey": false,
          "notNull": true,
          "autoincrement": false
        },
        "response_title": {
          "name": "response_title",
          "type": "text",
          "primaryKey": false,
          "notNull": true,
          "autoincrement": false
        },
        "response_body_json": {
          "name": "response_body_json",
          "type": "text",
          "primaryKey": false,
          "notNull": true,
          "autoincrement": false
        },
        "created_at": {
          "name": "created_at",
          "type": "text",
          "primaryKey": false,
          "notNull": true,
          "autoincrement": false
        }
      },
      "indexes": {},
      "foreignKeys": {},
      "compositePrimaryKeys": {},
      "uniqueConstraints": {},
      "checkConstraints": {}
    },
    "issue_events": {
      "name": "issue_events",
      "columns": {
        "id": {
          "name": "id",
          "type": "text",
          "primaryKey": true,
          "notNull": true,
          "autoincrement": false
        },
        "issue_key": {
          "name": "issue_key",
          "type": "text",
          "primaryKey": false,
          "notNull": true,
          "autoincrement": false
        },
        "type": {
          "name": "type",
          "type": "text",
          "primaryKey": false,
          "notNull": true,
          "autoincrement": false
        },
        "actor_id": {
          "name": "actor_id",
          "type": "text",
          "primaryKey": false,
          "notNull": false,
          "autoincrement": false
        },
        "message": {
          "name": "message",
          "type": "text",
          "primaryKey": false,
          "notNull": true,
          "autoincrement": false
        },
        "created_at": {
          "name": "created_at",
          "type": "text",
          "primaryKey": false,
          "notNull": true,
          "autoincrement": false
        }
      },
      "indexes": {},
      "foreignKeys": {
        "issue_events_issue_key_issues_key_fk": {
          "name": "issue_events_issue_key_issues_key_fk",
          "tableFrom": "issue_events",
          "tableTo": "issues",
          "columnsFrom": [
            "issue_key"
          ],
          "columnsTo": [
            "key"
          ],
          "onDelete": "cascade",
          "onUpdate": "no action"
        },
        "issue_events_actor_id_members_id_fk": {
          "name": "issue_events_actor_id_members_id_fk",
          "tableFrom": "issue_events",
          "tableTo": "members",
          "columnsFrom": [
            "actor_id"
          ],
          "columnsTo": [
            "id"
          ],
          "onDelete": "no action",
          "onUpdate": "no action"
        }
      },
      "compositePrimaryKeys": {},
      "uniqueConstraints": {},
      "checkConstraints": {}
    },
    "issues": {
      "name": "issues",
      "columns": {
        "key": {
          "name": "key",
          "type": "text",
          "primaryKey": true,
          "notNull": true,
          "autoincrement": false
        },
        "project_id": {
          "name": "project_id",
          "type": "text",
          "primaryKey": false,
          "notNull": true,
          "autoincrement": false
        },
        "iteration_id": {
          "name": "iteration_id",
          "type": "text",
          "primaryKey": false,
          "notNull": true,
          "autoincrement": false
        },
        "type": {
          "name": "type",
          "type": "text",
          "primaryKey": false,
          "notNull": true,
          "autoincrement": false
        },
        "title": {
          "name": "title",
          "type": "text",
          "primaryKey": false,
          "notNull": true,
          "autoincrement": false
        },
        "status": {
          "name": "status",
          "type": "text",
          "primaryKey": false,
          "notNull": true,
          "autoincrement": false
        },
        "priority": {
          "name": "priority",
          "type": "text",
          "primaryKey": false,
          "notNull": true,
          "autoincrement": false
        },
        "assignee_id": {
          "name": "assignee_id",
          "type": "text",
          "primaryKey": false,
          "notNull": true,
          "autoincrement": false
        },
        "story_points": {
          "name": "story_points",
          "type": "integer",
          "primaryKey": false,
          "notNull": true,
          "autoincrement": false
        },
        "blocker_reason": {
          "name": "blocker_reason",
          "type": "text",
          "primaryKey": false,
          "notNull": false,
          "autoincrement": false
        }
      },
      "indexes": {
        "issues_project_status": {
          "name": "issues_project_status",
          "columns": [
            "project_id",
            "status"
          ],
          "isUnique": false
        },
        "issues_assignee": {
          "name": "issues_assignee",
          "columns": [
            "assignee_id"
          ],
          "isUnique": false
        }
      },
      "foreignKeys": {
        "issues_project_id_projects_id_fk": {
          "name": "issues_project_id_projects_id_fk",
          "tableFrom": "issues",
          "tableTo": "projects",
          "columnsFrom": [
            "project_id"
          ],
          "columnsTo": [
            "id"
          ],
          "onDelete": "cascade",
          "onUpdate": "no action"
        },
        "issues_iteration_id_iterations_id_fk": {
          "name": "issues_iteration_id_iterations_id_fk",
          "tableFrom": "issues",
          "tableTo": "iterations",
          "columnsFrom": [
            "iteration_id"
          ],
          "columnsTo": [
            "id"
          ],
          "onDelete": "cascade",
          "onUpdate": "no action"
        },
        "issues_assignee_id_members_id_fk": {
          "name": "issues_assignee_id_members_id_fk",
          "tableFrom": "issues",
          "tableTo": "members",
          "columnsFrom": [
            "assignee_id"
          ],
          "columnsTo": [
            "id"
          ],
          "onDelete": "no action",
          "onUpdate": "no action"
        }
      },
      "compositePrimaryKeys": {},
      "uniqueConstraints": {},
      "checkConstraints": {}
    },
    "iterations": {
      "name": "iterations",
      "columns": {
        "id": {
          "name": "id",
          "type": "text",
          "primaryKey": true,
          "notNull": true,
          "autoincrement": false
        },
        "project_id": {
          "name": "project_id",
          "type": "text",
          "primaryKey": false,
          "notNull": true,
          "autoincrement": false
        },
        "code": {
          "name": "code",
          "type": "text",
          "primaryKey": false,
          "notNull": true,
          "autoincrement": false
        },
        "name": {
          "name": "name",
          "type": "text",
          "primaryKey": false,
          "notNull": true,
          "autoincrement": false
        },
        "day": {
          "name": "day",
          "type": "integer",
          "primaryKey": false,
          "notNull": true,
          "autoincrement": false
        },
        "total_days": {
          "name": "total_days",
          "type": "integer",
          "primaryKey": false,
          "notNull": true,
          "autoincrement": false
        },
        "goal": {
          "name": "goal",
          "type": "text",
          "primaryKey": false,
          "notNull": true,
          "autoincrement": false
        },
        "velocity": {
          "name": "velocity",
          "type": "integer",
          "primaryKey": false,
          "notNull": true,
          "autoincrement": false
        }
      },
      "indexes": {
        "iterations_project_code": {
          "name": "iterations_project_code",
          "columns": [
            "project_id",
            "code"
          ],
          "isUnique": true
        }
      },
      "foreignKeys": {
        "iterations_project_id_projects_id_fk": {
          "name": "iterations_project_id_projects_id_fk",
          "tableFrom": "iterations",
          "tableTo": "projects",
          "columnsFrom": [
            "project_id"
          ],
          "columnsTo": [
            "id"
          ],
          "onDelete": "cascade",
          "onUpdate": "no action"
        }
      },
      "compositePrimaryKeys": {},
      "uniqueConstraints": {},
      "checkConstraints": {}
    },
    "members": {
      "name": "members",
      "columns": {
        "id": {
          "name": "id",
          "type": "text",
          "primaryKey": true,
          "notNull": true,
          "autoincrement": false
        },
        "name": {
          "name": "name",
          "type": "text",
          "primaryKey": false,
          "notNull": true,
          "autoincrement": false
        },
        "role": {
          "name": "role",
          "type": "text",
          "primaryKey": false,
          "notNull": true,
          "autoincrement": false
        },
        "capacity": {
          "name": "capacity",
          "type": "integer",
          "primaryKey": false,
          "notNull": true,
          "autoincrement": false
        }
      },
      "indexes": {},
      "foreignKeys": {},
      "compositePrimaryKeys": {},
      "uniqueConstraints": {},
      "checkConstraints": {}
    },
    "milestones": {
      "name": "milestones",
      "columns": {
        "id": {
          "name": "id",
          "type": "text",
          "primaryKey": true,
          "notNull": true,
          "autoincrement": false
        },
        "project_id": {
          "name": "project_id",
          "type": "text",
          "primaryKey": false,
          "notNull": true,
          "autoincrement": false
        },
        "iteration_id": {
          "name": "iteration_id",
          "type": "text",
          "primaryKey": false,
          "notNull": true,
          "autoincrement": false
        },
        "title": {
          "name": "title",
          "type": "text",
          "primaryKey": false,
          "notNull": true,
          "autoincrement": false
        },
        "start_day": {
          "name": "start_day",
          "type": "integer",
          "primaryKey": false,
          "notNull": true,
          "autoincrement": false
        },
        "end_day": {
          "name": "end_day",
          "type": "integer",
          "primaryKey": false,
          "notNull": true,
          "autoincrement": false
        },
        "status": {
          "name": "status",
          "type": "text",
          "primaryKey": false,
          "notNull": true,
          "autoincrement": false
        },
        "owner_id": {
          "name": "owner_id",
          "type": "text",
          "primaryKey": false,
          "notNull": true,
          "autoincrement": false
        }
      },
      "indexes": {},
      "foreignKeys": {
        "milestones_project_id_projects_id_fk": {
          "name": "milestones_project_id_projects_id_fk",
          "tableFrom": "milestones",
          "tableTo": "projects",
          "columnsFrom": [
            "project_id"
          ],
          "columnsTo": [
            "id"
          ],
          "onDelete": "cascade",
          "onUpdate": "no action"
        },
        "milestones_iteration_id_iterations_id_fk": {
          "name": "milestones_iteration_id_iterations_id_fk",
          "tableFrom": "milestones",
          "tableTo": "iterations",
          "columnsFrom": [
            "iteration_id"
          ],
          "columnsTo": [
            "id"
          ],
          "onDelete": "cascade",
          "onUpdate": "no action"
        },
        "milestones_owner_id_members_id_fk": {
          "name": "milestones_owner_id_members_id_fk",
          "tableFrom": "milestones",
          "tableTo": "members",
          "columnsFrom": [
            "owner_id"
          ],
          "columnsTo": [
            "id"
          ],
          "onDelete": "no action",
          "onUpdate": "no action"
        }
      },
      "compositePrimaryKeys": {},
      "uniqueConstraints": {},
      "checkConstraints": {}
    },
    "projects": {
      "name": "projects",
      "columns": {
        "id": {
          "name": "id",
          "type": "text",
          "primaryKey": true,
          "notNull": true,
          "autoincrement": false
        },
        "name": {
          "name": "name",
          "type": "text",
          "primaryKey": false,
          "notNull": true,
          "autoincrement": false
        },
        "glyph": {
          "name": "glyph",
          "type": "text",
          "primaryKey": false,
          "notNull": true,
          "autoincrement": false
        },
        "color": {
          "name": "color",
          "type": "text",
          "primaryKey": false,
          "notNull": true,
          "autoincrement": false
        },
        "active_iteration_code": {
          "name": "active_iteration_code",
          "type": "text",
          "primaryKey": false,
          "notNull": true,
          "autoincrement": false
        }
      },
      "indexes": {},
      "foreignKeys": {},
      "compositePrimaryKeys": {},
      "uniqueConstraints": {},
      "checkConstraints": {}
    },
    "standup_items": {
      "name": "standup_items",
      "columns": {
        "id": {
          "name": "id",
          "type": "text",
          "primaryKey": true,
          "notNull": true,
          "autoincrement": false
        },
        "standup_id": {
          "name": "standup_id",
          "type": "text",
          "primaryKey": false,
          "notNull": true,
          "autoincrement": false
        },
        "member_id": {
          "name": "member_id",
          "type": "text",
          "primaryKey": false,
          "notNull": true,
          "autoincrement": false
        },
        "yesterday_json": {
          "name": "yesterday_json",
          "type": "text",
          "primaryKey": false,
          "notNull": true,
          "autoincrement": false
        },
        "today_json": {
          "name": "today_json",
          "type": "text",
          "primaryKey": false,
          "notNull": true,
          "autoincrement": false
        },
        "blockers_json": {
          "name": "blockers_json",
          "type": "text",
          "primaryKey": false,
          "notNull": true,
          "autoincrement": false
        }
      },
      "indexes": {},
      "foreignKeys": {
        "standup_items_standup_id_standups_id_fk": {
          "name": "standup_items_standup_id_standups_id_fk",
          "tableFrom": "standup_items",
          "tableTo": "standups",
          "columnsFrom": [
            "standup_id"
          ],
          "columnsTo": [
            "id"
          ],
          "onDelete": "cascade",
          "onUpdate": "no action"
        },
        "standup_items_member_id_members_id_fk": {
          "name": "standup_items_member_id_members_id_fk",
          "tableFrom": "standup_items",
          "tableTo": "members",
          "columnsFrom": [
            "member_id"
          ],
          "columnsTo": [
            "id"
          ],
          "onDelete": "no action",
          "onUpdate": "no action"
        }
      },
      "compositePrimaryKeys": {},
      "uniqueConstraints": {},
      "checkConstraints": {}
    },
    "standups": {
      "name": "standups",
      "columns": {
        "id": {
          "name": "id",
          "type": "text",
          "primaryKey": true,
          "notNull": true,
          "autoincrement": false
        },
        "project_id": {
          "name": "project_id",
          "type": "text",
          "primaryKey": false,
          "notNull": true,
          "autoincrement": false
        },
        "date_label": {
          "name": "date_label",
          "type": "text",
          "primaryKey": false,
          "notNull": true,
          "autoincrement": false
        },
        "time_label": {
          "name": "time_label",
          "type": "text",
          "primaryKey": false,
          "notNull": true,
          "autoincrement": false
        }
      },
      "indexes": {},
      "foreignKeys": {
        "standups_project_id_projects_id_fk": {
          "name": "standups_project_id_projects_id_fk",
          "tableFrom": "standups",
          "tableTo": "projects",
          "columnsFrom": [
            "project_id"
          ],
          "columnsTo": [
            "id"
          ],
          "onDelete": "cascade",
          "onUpdate": "no action"
        }
      },
      "compositePrimaryKeys": {},
      "uniqueConstraints": {},
      "checkConstraints": {}
    }
  },
  "views": {},
  "enums": {},
  "_meta": {
    "schemas": {},
    "tables": {},
    "columns": {}
  },
  "internal": {
    "indexes": {}
  }
}